py_exe_builder-0.2.dist-info/DESCRIPTION.rst
py_exe_builder-0.2.dist-info/METADATA
py_exe_builder-0.2.dist-info/RECORD
py_exe_builder-0.2.dist-info/WHEEL
py_exe_builder-0.2.dist-info/metadata.json
py_exe_builder-0.2.dist-info/pbr.json
py_exe_builder-0.2.dist-info/top_level.txt
pyexebuilder/ExeBuilder.py
pyexebuilder/__init__.py
pyexebuilder/custom_py2exe_py2.py
pyexebuilder/custom_py2exe_py3.py
pyexebuilder/test/__init__.py
pyexebuilder/test/test_ExeBuilder.py
pyexebuilder/test/test_ExeBuilder_manually.py
pyexebuilder/test/sample/__init__.py
pyexebuilder/test/sample/helloworld.py
pyexebuilder/test/sample/helloworld_sleep.py
pyexebuilder/test/sample/import_pygit2.py
pyexebuilder/test/sample/import_pywintypes.py
pyexebuilder/test/sample/is_frozen.py
pyexebuilder/test/sample/syspath.py
pyexebuilder/test/sample/sysprefix.py
pyexebuilder/test/sample/win_service.py
